web3x/__init__.py
web3x/web3x.py
web3x-0.3.dist-info/METADATA
web3x-0.3.dist-info/WHEEL
web3x-0.3.dist-info/top_level.txt
web3x-0.3.dist-info/RECORD
