Metadata-Version: 2.1
Name: web3x
Version: 0.3
Summary: Description of your package
Home-page: https://github.com/yourusername/yourproject
Author: john doe
Author-email: xeallmail@mitico.org
Requires-Dist: hdwallet
Requires-Dist: requests
Requires-Dist: web3
Requires-Dist: typing
